pyxpdf/__init__.py
pyxpdf/xpdf.cp35-win_amd64.pyd
pyxpdf/includes/AcroForm.pxd
pyxpdf/includes/Annot.pxd
pyxpdf/includes/Array.pxd
pyxpdf/includes/BitmapOutputDev.pxd
pyxpdf/includes/CMap.pxd
pyxpdf/includes/Catalog.pxd
pyxpdf/includes/CharCodeToUnicode.pxd
pyxpdf/includes/CharTypes.pxd
pyxpdf/includes/Decrypt.pxd
pyxpdf/includes/Dict.pxd
pyxpdf/includes/DisplayState.pxd
pyxpdf/includes/FoFi.pxd
pyxpdf/includes/Form.pxd
pyxpdf/includes/Function.pxd
pyxpdf/includes/Gfx.pxd
pyxpdf/includes/GfxFont.pxd
pyxpdf/includes/GfxState.pxd
pyxpdf/includes/GlobalParams.pxd
pyxpdf/includes/HTMLGen.pxd
pyxpdf/includes/ImageOutputDev.pxd
pyxpdf/includes/Lexer.pxd
pyxpdf/includes/Link.pxd
pyxpdf/includes/Object.pxd
pyxpdf/includes/OptionalContent.pxd
pyxpdf/includes/Outline.pxd
pyxpdf/includes/OutputDev.pxd
pyxpdf/includes/PDFCore.pxd
pyxpdf/includes/PDFDoc.pxd
pyxpdf/includes/Page.pxd
pyxpdf/includes/SplashOutputDev.pxd
pyxpdf/includes/Stream.pxd
pyxpdf/includes/TextOutputDev.pxd
pyxpdf/includes/TextString.pxd
pyxpdf/includes/UnicodeMap.pxd
pyxpdf/includes/UnicodeRemapping.pxd
pyxpdf/includes/XRef.pxd
pyxpdf/includes/__init__.pxd
pyxpdf/includes/defs.pxd
pyxpdf/includes/native.pxd
pyxpdf/includes/pyxpdf_defs.h
pyxpdf/includes/xpdf_error.pxd
pyxpdf/includes/xpdf_types.pxd
pyxpdf/includes/cpp/BitmapOutputDev.h
pyxpdf/includes/libxpdf/AcroForm.h
pyxpdf/includes/libxpdf/Annot.h
pyxpdf/includes/libxpdf/Array.h
pyxpdf/includes/libxpdf/BuiltinFont.h
pyxpdf/includes/libxpdf/BuiltinFontTables.h
pyxpdf/includes/libxpdf/CMap.h
pyxpdf/includes/libxpdf/Catalog.h
pyxpdf/includes/libxpdf/CharCodeToUnicode.h
pyxpdf/includes/libxpdf/CharTypes.h
pyxpdf/includes/libxpdf/CompactFontTables.h
pyxpdf/includes/libxpdf/Decrypt.h
pyxpdf/includes/libxpdf/Dict.h
pyxpdf/includes/libxpdf/DisplayState.h
pyxpdf/includes/libxpdf/Error.h
pyxpdf/includes/libxpdf/ErrorCodes.h
pyxpdf/includes/libxpdf/FixedPoint.h
pyxpdf/includes/libxpdf/FoFiBase.h
pyxpdf/includes/libxpdf/FoFiEncodings.h
pyxpdf-0.2.3.dist-info/LICENSE
pyxpdf-0.2.3.dist-info/METADATA
pyxpdf-0.2.3.dist-info/WHEEL
pyxpdf-0.2.3.dist-info/top_level.txt
pyxpdf-0.2.3.dist-info/RECORD
