Metadata-Version: 2.1
Name: pyxpdf
Version: 0.2.3
Summary: Powerful and Pythonic PDF processing library based on xpdf-4.02
Home-page: https://github.com/ashutoshvarma/pyxpdf
Author: Ashutosh Varma
Author-email: ashutoshvarma11@live.com
Maintainer: Ashutosh Varma
Maintainer-email: ashutoshvarma11@live.com
License: GPL
Keywords: pdf parser,pdf converter,text mining,xpdf bindings
Platform: UNKNOWN
Classifier: Development Status :: 5 - Production/Stable
Classifier: Intended Audience :: Developers
Classifier: Intended Audience :: Information Technology
Classifier: Intended Audience :: Science/Research
Classifier: License :: OSI Approved :: GNU General Public License v3 (GPLv3)
Classifier: Programming Language :: Cython
Classifier: Programming Language :: Python :: 3
Classifier: Programming Language :: Python :: 3.5
Classifier: Programming Language :: Python :: 3.6
Classifier: Programming Language :: Python :: 3.7
Classifier: Programming Language :: Python :: 3.8
Classifier: Programming Language :: C++
Classifier: Operating System :: OS Independent
Classifier: Topic :: Software Development :: Libraries :: Python Modules
Classifier: Topic :: Text Processing
Requires-Python: !=3.0.*, !=3.1.*, !=3.2.*, !=3.3.*, != 3.4.*
Provides-Extra: dev
Requires-Dist: cython ; extra == 'dev'
Provides-Extra: encoding
Requires-Dist: pyxpdf-data ; extra == 'encoding'
Provides-Extra: imaging
Requires-Dist: Pillow ; extra == 'imaging'
Provides-Extra: source
Requires-Dist: Cython (>=0.29.7) ; extra == 'source'
